offlinemsmtp/__init__.py
offlinemsmtp/__main__.py
offlinemsmtp/daemon.py
offlinemsmtp/util.py
offlinemsmtp-0.4.0.dist-info/entry_points.txt
offlinemsmtp-0.4.0.dist-info/LICENSE
offlinemsmtp-0.4.0.dist-info/WHEEL
offlinemsmtp-0.4.0.dist-info/METADATA
offlinemsmtp-0.4.0.dist-info/RECORD
