Metadata-Version: 2.1
Name: offlinemsmtp
Version: 0.4.0
Summary: msmtp wrapper allowing for offline use
Home-page: https://github.com/sumnerevans/offlinemsmtp
License: GPL-3.0-or-later
Keywords: email,msmtp,offline
Author: Sumner Evans
Author-email: inquiries@sumnerevans.com
Requires-Python: >=3.8,<4.0
Classifier: Development Status :: 3 - Alpha
Classifier: Intended Audience :: End Users/Desktop
Classifier: License :: OSI Approved :: GNU General Public License v3 or later (GPLv3+)
Classifier: Operating System :: POSIX
Classifier: Programming Language :: Python :: 3
Classifier: Programming Language :: Python :: 3.8
Classifier: Programming Language :: Python :: 3.9
Classifier: Programming Language :: Python :: 3.10
Classifier: Programming Language :: Python :: 3.11
Classifier: Topic :: Communications :: Email :: Mail Transport Agents
Requires-Dist: inotify (>=0.2.10,<0.3.0)
Project-URL: Bug Tracker, https://github.com/sumnerevans/offlinemsmtp/issues
Project-URL: Repository, https://github.com/sumnerevans/offlinemsmtp
